filmAneesdk/__init__.py
filmAneesdk/film_client.py
filmAneesdk/film_config.py
filmAneesdk/schemas/__init__.py
filmAneesdk/schemas/schemas.py
filmaneesdk-0.0.9.dist-info/METADATA
filmaneesdk-0.0.9.dist-info/WHEEL
filmaneesdk-0.0.9.dist-info/top_level.txt
filmaneesdk-0.0.9.dist-info/RECORD
